ud2ude/__init__.py
ud2ude/api.py
ud2ude/conllu_wrapper.py
ud2ude/converter.py
ud2ude/graph_token.py
ud2ude/matcher.py
ud2ude_aryehgigi/__init__.py
ud2ude_aryehgigi/api.py
ud2ude_aryehgigi/conllu_wrapper.py
ud2ude_aryehgigi/converter.py
ud2ude_aryehgigi/graph_token.py
ud2ude_aryehgigi/matcher.py
ud2ude_aryehgigi-2.0.1.dist-info/LICENSE
ud2ude_aryehgigi-2.0.1.dist-info/METADATA
ud2ude_aryehgigi-2.0.1.dist-info/WHEEL
ud2ude_aryehgigi-2.0.1.dist-info/top_level.txt
ud2ude_aryehgigi-2.0.1.dist-info/RECORD
