Metadata-Version: 2.1
Name: ud2ude-aryehgigi
Version: 2.0.1
Summary: python converter from UD to enhanced UD representations
Home-page: https://github.com/aryehgigi/UD2UDE
Author: Aryeh Tiktinsky
Author-email: aryehgigi@gmail.com
License: UNKNOWN
Platform: UNKNOWN
Classifier: Programming Language :: Python :: 3
Classifier: License :: OSI Approved :: Apache Software License
Classifier: Operating System :: OS Independent
Requires-Python: >=3.6
